tol/__init__.py
tol/cert.py
tol/deb.py
tol/fs.py
tol/git.py
tol/lxd.py
tol/mysql.py
tol/postgres.py
tol/user.py
tol-0.1.0.dist-info/LICENSE
tol-0.1.0.dist-info/METADATA
tol-0.1.0.dist-info/WHEEL
tol-0.1.0.dist-info/top_level.txt
tol-0.1.0.dist-info/RECORD
