Metadata-Version: 2.1
Name: tol
Version: 0.1.0
Summary: tøl n1 (norrønt tól 'reiskap') kollektivt: (små)saker
Home-page: https://github.com/beat-no/tol
Author: Øystein S. Haaland
Author-email: oystein@beat.no
License: UNKNOWN
Platform: UNKNOWN
